dict_lookup_mpnn_problem/__init__.py
dict_lookup_mpnn_problem/generate.py
dict_lookup_mpnn_problem-0.1.1.dist-info/METADATA
dict_lookup_mpnn_problem-0.1.1.dist-info/WHEEL
dict_lookup_mpnn_problem-0.1.1.dist-info/licenses/LICENSE
dict_lookup_mpnn_problem-0.1.1.dist-info/RECORD
