Metadata-Version: 2.3
Name: dict-lookup-mpnn-problem
Version: 0.1.1
Summary: Add your description here
Author-email: Marcell Vazquez-Chanlatte <mvc@linux.com>
License-File: LICENSE
Requires-Python: >=3.11
Requires-Dist: numpy>=2.1.2
